{"chunk_definitions":[{"row":22,"row_count":1,"visible":true,"expansion_state":0,"options":{"engine":"r","label":"plotpavos","include":true,"fig.align":"center","fig.cap":"Datos pavos. Diagrama de dispersión."},"document_id":"F677710E","chunk_id":"c53l6iujr7evt","chunk_label":"plotpavos"},{"row":48,"row_count":1,"visible":true,"expansion_state":0,"options":{"engine":"r","label":"plotpurom","include":true,"fig.align":"center","fig.height":5,"fig.width":8,"fig.cap":"Daros Puromicina. Diagrama de dispersión: Relación entre la velocidad de reacción y la concentración de sustrato. Encimas tratadas(puntos negros), Encimas no tratadas(puntos rojos)"},"document_id":"F677710E","chunk_id":"cs0thmb4t425b","chunk_label":"plotpurom"},{"row":59,"row_count":1,"visible":true,"expansion_state":0,"options":{"engine":"r","label":"modMichMen","fig.align":"center","out.width":"75%","echo":false,"fig.cap":"Modelo Michaelis-Menten"},"document_id":"F677710E","chunk_id":"csvz0brga54ct","chunk_label":"modMichMen"},{"row":245,"row_count":1,"visible":true,"expansion_state":0,"options":{"engine":"r"},"document_id":"F677710E","chunk_id":"cefsitdx65cul","chunk_label":"plotpavoscrec"},{"row":283,"row_count":1,"visible":true,"expansion_state":0,"options":{"engine":"r","label":"tablapavos","include":true},"document_id":"F677710E","chunk_id":"cv32tplwoy8qq","chunk_label":"tablapavos"},{"row":320,"row_count":1,"visible":true,"expansion_state":0,"options":{"engine":"r","label":"tresmodelospavos","include":true,"fig.align":"center","fig.cap":"Datos crecimiento de pavos. Ajuste del modelo de crecimiento propuesto (rojo), modelo logístico (verde) y Modelo Weibull (azul)."},"document_id":"F677710E","chunk_id":"cl70piq0kt9y2","chunk_label":"tresmodelospavos"},{"row":338,"row_count":1,"visible":true,"expansion_state":0,"options":{"engine":"r","label":"linealpuromicina","echo":false,"include":true,"fig.align":"center","fig.cap":"Datos puromicina. Diagrama de dispersión. Datos linealizados(derecha)."},"document_id":"F677710E","chunk_id":"crgxsyxinir61","chunk_label":"linealpuromicina"},{"row":359,"row_count":1,"visible":true,"expansion_state":0,"options":{"engine":"r","label":"tablapuromicina","include":true},"document_id":"F677710E","chunk_id":"cgontxzxx2uu0","chunk_label":"tablapuromicina"},{"row":372,"row_count":1,"visible":true,"expansion_state":0,"options":{"engine":"r","label":"puromicinaplotl","include":true,"fig.align":"center","fig.cap":"Datos puromicina. Enzimas tratadas(negro), enzimas no tratadas(rojo). "},"document_id":"F677710E","chunk_id":"c9ejkg3pj8ahe","chunk_label":"puromicinaplotl"}],"doc_write_time":1675872917}